MANIFEST.in
setup.cfg
setup.py
stratus_api/bigquery/__init__.py
stratus_api/bigquery/base.py
stratus_api/bigquery/bigquery.py
stratus_api/bigquery/utilities.py
stratus_api/bigquery/schemas/bigquery.yaml
stratus_api_bigquery.egg-info/PKG-INFO
stratus_api_bigquery.egg-info/SOURCES.txt
stratus_api_bigquery.egg-info/dependency_links.txt
stratus_api_bigquery.egg-info/requires.txt
stratus_api_bigquery.egg-info/top_level.txt